{
    "projects":[
        {
            "id":"1",
            "title": "Age Calculator",
            "description": "A Javascript calculator that works out your age based on your date of birth input.",
            "image":
                    {
                        "url": "assets/age-calc.png",
                        "width": 200,
                        "height": 200
                    } ,
            "url":"https://github.com/Richtbiscuitcoder/age-calculator"
        }
        ,
        {
            "id":"2",
            "title":"project-two",
            "description":"description of project 2",
            "image": "",
            "url":""
        }
        ,
        {
            "id":"3",
            "title": "project-three",
            "description": "description of project 3",
            "image": "",
            "url":""
        }
        ,
        {
            "id":"4",
            "title": "project-four",
            "description": "description of project 4",
            "image": "",
            "url":""
        }
    ]
}